isi_segmentation/__init__.py
isi_segmentation/plot.py
isi_segmentation/postprocess.py
isi_segmentation/prediction.py
isi_segmentation/types.py
isi_segmentation/utils.py
isi_segmentation-0.1.1.dist-info/LICENSE
isi_segmentation-0.1.1.dist-info/METADATA
isi_segmentation-0.1.1.dist-info/WHEEL
isi_segmentation-0.1.1.dist-info/top_level.txt
isi_segmentation-0.1.1.dist-info/RECORD
