Metadata-Version: 2.1
Name: isi_segmentation
Version: 0.1.1
Summary: Supervised ISI segmentaion using tensorflow
Home-page: https://github.com/AllenNeuralDynamics/isi_segmentation
Author: Di Wang
Author-email: di.wang@alleninstitute.org
Keywords: deep learning,computer vision
Requires-Python: >=3.7
License-File: LICENSE
Requires-Dist: scipy
Requires-Dist: opencv-python
Requires-Dist: gdown
Requires-Dist: matplotlib
Requires-Dist: tensorflow ==2.9.0
